{
  "type": "File",
  "start": 0,
  "end": 140,
  "loc": {
    "start": {
      "line": 1,
      "column": 0
    },
    "end": {
      "line": 2,
      "column": 60
    }
  },
  "program": {
    "type": "Program",
    "start": 0,
    "end": 140,
    "loc": {
      "start": {
        "line": 1,
        "column": 0
      },
      "end": {
        "line": 2,
        "column": 60
      }
    },
    "sourceType": "module",
    "body": [
      {
        "type": "ExportNamedDeclaration",
        "start": 0,
        "end": 79,
        "loc": {
          "start": {
            "line": 1,
            "column": 0
          },
          "end": {
            "line": 1,
            "column": 79
          }
        },
        "declaration": null,
        "specifiers": [
          {
            "type": "ExportSpecifier",
            "start": 9,
            "end": 41,
            "loc": {
              "start": {
                "line": 1,
                "column": 9
              },
              "end": {
                "line": 1,
                "column": 41
              }
            },
            "local": {
              "type": "Identifier",
              "start": 9,
              "end": 16,
              "loc": {
                "start": {
                  "line": 1,
                  "column": 9
                },
                "end": {
                  "line": 1,
                  "column": 16
                },
                "identifierName": "default"
              },
              "name": "default"
            },
            "exported": {
              "type": "Identifier",
              "start": 20,
              "end": 41,
              "loc": {
                "start": {
                  "line": 1,
                  "column": 20
                },
                "end": {
                  "line": 1,
                  "column": 41
                },
                "identifierName": "causalNetSGDOptimizer"
              },
              "name": "causalNetSGDOptimizer"
            }
          }
        ],
        "source": {
          "type": "StringLiteral",
          "start": 49,
          "end": 78,
          "loc": {
            "start": {
              "line": 1,
              "column": 49
            },
            "end": {
              "line": 1,
              "column": 78
            }
          },
          "extra": {
            "rawValue": "./StochasticGradientDescent",
            "raw": "'./StochasticGradientDescent'"
          },
          "value": "./StochasticGradientDescent"
        }
      },
      {
        "type": "ExportNamedDeclaration",
        "start": 80,
        "end": 140,
        "loc": {
          "start": {
            "line": 2,
            "column": 0
          },
          "end": {
            "line": 2,
            "column": 60
          }
        },
        "declaration": null,
        "specifiers": [
          {
            "type": "ExportSpecifier",
            "start": 89,
            "end": 113,
            "loc": {
              "start": {
                "line": 2,
                "column": 9
              },
              "end": {
                "line": 2,
                "column": 33
              }
            },
            "local": {
              "type": "Identifier",
              "start": 89,
              "end": 96,
              "loc": {
                "start": {
                  "line": 2,
                  "column": 9
                },
                "end": {
                  "line": 2,
                  "column": 16
                },
                "identifierName": "default"
              },
              "name": "default"
            },
            "exported": {
              "type": "Identifier",
              "start": 100,
              "end": 113,
              "loc": {
                "start": {
                  "line": 2,
                  "column": 20
                },
                "end": {
                  "line": 2,
                  "column": 33
                },
                "identifierName": "TrainerMixins"
              },
              "name": "TrainerMixins"
            }
          }
        ],
        "source": {
          "type": "StringLiteral",
          "start": 121,
          "end": 139,
          "loc": {
            "start": {
              "line": 2,
              "column": 41
            },
            "end": {
              "line": 2,
              "column": 59
            }
          },
          "extra": {
            "rawValue": "./trainer.mixins",
            "raw": "'./trainer.mixins'"
          },
          "value": "./trainer.mixins"
        }
      }
    ],
    "directives": []
  },
  "comments": [],
  "tokens": [
    {
      "type": {
        "label": "export",
        "keyword": "export",
        "beforeExpr": false,
        "startsExpr": false,
        "rightAssociative": false,
        "isLoop": false,
        "isAssign": false,
        "prefix": false,
        "postfix": false,
        "binop": null,
        "updateContext": null
      },
      "value": "export",
      "start": 0,
      "end": 6,
      "loc": {
        "start": {
          "line": 1,
          "column": 0
        },
        "end": {
          "line": 1,
          "column": 6
        }
      }
    },
    {
      "type": {
        "label": "{",
        "beforeExpr": true,
        "startsExpr": true,
        "rightAssociative": false,
        "isLoop": false,
        "isAssign": false,
        "prefix": false,
        "postfix": false,
        "binop": null
      },
      "start": 7,
      "end": 8,
      "loc": {
        "start": {
          "line": 1,
          "column": 7
        },
        "end": {
          "line": 1,
          "column": 8
        }
      }
    },
    {
      "type": {
        "label": "default",
        "keyword": "default",
        "beforeExpr": true,
        "startsExpr": false,
        "rightAssociative": false,
        "isLoop": false,
        "isAssign": false,
        "prefix": false,
        "postfix": false,
        "binop": null,
        "updateContext": null
      },
      "value": "default",
      "start": 9,
      "end": 16,
      "loc": {
        "start": {
          "line": 1,
          "column": 9
        },
        "end": {
          "line": 1,
          "column": 16
        }
      }
    },
    {
      "type": {
        "label": "name",
        "beforeExpr": false,
        "startsExpr": true,
        "rightAssociative": false,
        "isLoop": false,
        "isAssign": false,
        "prefix": false,
        "postfix": false,
        "binop": null
      },
      "value": "as",
      "start": 17,
      "end": 19,
      "loc": {
        "start": {
          "line": 1,
          "column": 17
        },
        "end": {
          "line": 1,
          "column": 19
        }
      }
    },
    {
      "type": {
        "label": "name",
        "beforeExpr": false,
        "startsExpr": true,
        "rightAssociative": false,
        "isLoop": false,
        "isAssign": false,
        "prefix": false,
        "postfix": false,
        "binop": null
      },
      "value": "causalNetSGDOptimizer",
      "start": 20,
      "end": 41,
      "loc": {
        "start": {
          "line": 1,
          "column": 20
        },
        "end": {
          "line": 1,
          "column": 41
        }
      }
    },
    {
      "type": {
        "label": "}",
        "beforeExpr": false,
        "startsExpr": false,
        "rightAssociative": false,
        "isLoop": false,
        "isAssign": false,
        "prefix": false,
        "postfix": false,
        "binop": null
      },
      "start": 42,
      "end": 43,
      "loc": {
        "start": {
          "line": 1,
          "column": 42
        },
        "end": {
          "line": 1,
          "column": 43
        }
      }
    },
    {
      "type": {
        "label": "name",
        "beforeExpr": false,
        "startsExpr": true,
        "rightAssociative": false,
        "isLoop": false,
        "isAssign": false,
        "prefix": false,
        "postfix": false,
        "binop": null
      },
      "value": "from",
      "start": 44,
      "end": 48,
      "loc": {
        "start": {
          "line": 1,
          "column": 44
        },
        "end": {
          "line": 1,
          "column": 48
        }
      }
    },
    {
      "type": {
        "label": "string",
        "beforeExpr": false,
        "startsExpr": true,
        "rightAssociative": false,
        "isLoop": false,
        "isAssign": false,
        "prefix": false,
        "postfix": false,
        "binop": null,
        "updateContext": null
      },
      "value": "./StochasticGradientDescent",
      "start": 49,
      "end": 78,
      "loc": {
        "start": {
          "line": 1,
          "column": 49
        },
        "end": {
          "line": 1,
          "column": 78
        }
      }
    },
    {
      "type": {
        "label": ";",
        "beforeExpr": true,
        "startsExpr": false,
        "rightAssociative": false,
        "isLoop": false,
        "isAssign": false,
        "prefix": false,
        "postfix": false,
        "binop": null,
        "updateContext": null
      },
      "start": 78,
      "end": 79,
      "loc": {
        "start": {
          "line": 1,
          "column": 78
        },
        "end": {
          "line": 1,
          "column": 79
        }
      }
    },
    {
      "type": {
        "label": "export",
        "keyword": "export",
        "beforeExpr": false,
        "startsExpr": false,
        "rightAssociative": false,
        "isLoop": false,
        "isAssign": false,
        "prefix": false,
        "postfix": false,
        "binop": null,
        "updateContext": null
      },
      "value": "export",
      "start": 80,
      "end": 86,
      "loc": {
        "start": {
          "line": 2,
          "column": 0
        },
        "end": {
          "line": 2,
          "column": 6
        }
      }
    },
    {
      "type": {
        "label": "{",
        "beforeExpr": true,
        "startsExpr": true,
        "rightAssociative": false,
        "isLoop": false,
        "isAssign": false,
        "prefix": false,
        "postfix": false,
        "binop": null
      },
      "start": 87,
      "end": 88,
      "loc": {
        "start": {
          "line": 2,
          "column": 7
        },
        "end": {
          "line": 2,
          "column": 8
        }
      }
    },
    {
      "type": {
        "label": "default",
        "keyword": "default",
        "beforeExpr": true,
        "startsExpr": false,
        "rightAssociative": false,
        "isLoop": false,
        "isAssign": false,
        "prefix": false,
        "postfix": false,
        "binop": null,
        "updateContext": null
      },
      "value": "default",
      "start": 89,
      "end": 96,
      "loc": {
        "start": {
          "line": 2,
          "column": 9
        },
        "end": {
          "line": 2,
          "column": 16
        }
      }
    },
    {
      "type": {
        "label": "name",
        "beforeExpr": false,
        "startsExpr": true,
        "rightAssociative": false,
        "isLoop": false,
        "isAssign": false,
        "prefix": false,
        "postfix": false,
        "binop": null
      },
      "value": "as",
      "start": 97,
      "end": 99,
      "loc": {
        "start": {
          "line": 2,
          "column": 17
        },
        "end": {
          "line": 2,
          "column": 19
        }
      }
    },
    {
      "type": {
        "label": "name",
        "beforeExpr": false,
        "startsExpr": true,
        "rightAssociative": false,
        "isLoop": false,
        "isAssign": false,
        "prefix": false,
        "postfix": false,
        "binop": null
      },
      "value": "TrainerMixins",
      "start": 100,
      "end": 113,
      "loc": {
        "start": {
          "line": 2,
          "column": 20
        },
        "end": {
          "line": 2,
          "column": 33
        }
      }
    },
    {
      "type": {
        "label": "}",
        "beforeExpr": false,
        "startsExpr": false,
        "rightAssociative": false,
        "isLoop": false,
        "isAssign": false,
        "prefix": false,
        "postfix": false,
        "binop": null
      },
      "start": 114,
      "end": 115,
      "loc": {
        "start": {
          "line": 2,
          "column": 34
        },
        "end": {
          "line": 2,
          "column": 35
        }
      }
    },
    {
      "type": {
        "label": "name",
        "beforeExpr": false,
        "startsExpr": true,
        "rightAssociative": false,
        "isLoop": false,
        "isAssign": false,
        "prefix": false,
        "postfix": false,
        "binop": null
      },
      "value": "from",
      "start": 116,
      "end": 120,
      "loc": {
        "start": {
          "line": 2,
          "column": 36
        },
        "end": {
          "line": 2,
          "column": 40
        }
      }
    },
    {
      "type": {
        "label": "string",
        "beforeExpr": false,
        "startsExpr": true,
        "rightAssociative": false,
        "isLoop": false,
        "isAssign": false,
        "prefix": false,
        "postfix": false,
        "binop": null,
        "updateContext": null
      },
      "value": "./trainer.mixins",
      "start": 121,
      "end": 139,
      "loc": {
        "start": {
          "line": 2,
          "column": 41
        },
        "end": {
          "line": 2,
          "column": 59
        }
      }
    },
    {
      "type": {
        "label": ";",
        "beforeExpr": true,
        "startsExpr": false,
        "rightAssociative": false,
        "isLoop": false,
        "isAssign": false,
        "prefix": false,
        "postfix": false,
        "binop": null,
        "updateContext": null
      },
      "start": 139,
      "end": 140,
      "loc": {
        "start": {
          "line": 2,
          "column": 59
        },
        "end": {
          "line": 2,
          "column": 60
        }
      }
    },
    {
      "type": {
        "label": "eof",
        "beforeExpr": false,
        "startsExpr": false,
        "rightAssociative": false,
        "isLoop": false,
        "isAssign": false,
        "prefix": false,
        "postfix": false,
        "binop": null,
        "updateContext": null
      },
      "start": 140,
      "end": 140,
      "loc": {
        "start": {
          "line": 2,
          "column": 60
        },
        "end": {
          "line": 2,
          "column": 60
        }
      }
    }
  ]
}